predictor/__init__.py
predictor/app.py
predictor/models.py
predictor/prediction.py
predictor/utils.py
predictor/yoloseg/YOLOSeg.py
predictor/yoloseg/__init__.py
predictor/yoloseg/utils.py
fairpredictor-0.3.15.dist-info/METADATA
fairpredictor-0.3.15.dist-info/WHEEL
fairpredictor-0.3.15.dist-info/licenses/LICENSE
fairpredictor-0.3.15.dist-info/RECORD
