Metadata-Version: 2.4
Name: fairpredictor
Version: 0.3.15
Summary: A package for running predictions using fAIr
Author-email: kshitijrajsharma <skshitizraj@gmail.com>
License: MIT
License-File: LICENSE
Requires-Python: <4.0,>=3.9
Requires-Dist: ai-edge-litert>=1.2.0
Requires-Dist: geomltoolkits>=0.4.2
Requires-Dist: onnxruntime>=1.20.1
Requires-Dist: opencv-python-headless>=4.10.0.84
Requires-Dist: pillow>=9.1.0
Requires-Dist: requests>=2.32.3
Requires-Dist: scikit-image>=0.24.0
Requires-Dist: tqdm>=4.67.0
